coreapi-stubs/__init__.pyi
coreapi-stubs/codecs/__init__.pyi
coreapi-stubs/codecs/base.pyi
coreapi-stubs/compat.pyi
coreschema-stubs/__init__.pyi
coreschema-stubs/compat.pyi
coreschema-stubs/encodings/__init__.pyi
coreschema-stubs/encodings/corejson.pyi
coreschema-stubs/encodings/html.pyi
coreschema-stubs/encodings/jsonschema.pyi
coreschema-stubs/formats.pyi
coreschema-stubs/schemas.pyi
coreschema-stubs/utils.pyi
openapi_codec-stubs/__init__.pyi
openapi_codec-stubs/decode.pyi
openapi_codec-stubs/encode.pyi
openapi_codec-stubs/utils.pyi
rest_framework-stubs/__init__.pyi
rest_framework-stubs/apps.pyi
rest_framework-stubs/authentication.pyi
rest_framework-stubs/authtoken/__init__.pyi
rest_framework-stubs/authtoken/admin.pyi
rest_framework-stubs/authtoken/apps.pyi
rest_framework-stubs/authtoken/management/__init__.pyi
rest_framework-stubs/authtoken/management/commands/__init__.pyi
rest_framework-stubs/authtoken/management/commands/drf_create_token.pyi
rest_framework-stubs/authtoken/models.pyi
rest_framework-stubs/authtoken/serializers.pyi
rest_framework-stubs/authtoken/views.pyi
rest_framework-stubs/checks.pyi
rest_framework-stubs/compat.pyi
rest_framework-stubs/decorators.pyi
rest_framework-stubs/documentation.pyi
rest_framework-stubs/exceptions.pyi
rest_framework-stubs/fields.pyi
rest_framework-stubs/filters.pyi
rest_framework-stubs/generics.pyi
rest_framework-stubs/management/commands/generateschema.pyi
rest_framework-stubs/metadata.pyi
rest_framework-stubs/mixins.pyi
rest_framework-stubs/negotiation.pyi
rest_framework-stubs/pagination.pyi
rest_framework-stubs/parsers.pyi
rest_framework-stubs/permissions.pyi
rest_framework-stubs/relations.pyi
rest_framework-stubs/renderers.pyi
rest_framework-stubs/request.pyi
rest_framework-stubs/response.pyi
rest_framework-stubs/reverse.pyi
rest_framework-stubs/routers.pyi
rest_framework-stubs/schemas/__init__.pyi
rest_framework-stubs/schemas/coreapi.pyi
rest_framework-stubs/schemas/generators.pyi
djangorestframework_types-0.9.0.dist-info/LICENSE.txt
djangorestframework_types-0.9.0.dist-info/METADATA
djangorestframework_types-0.9.0.dist-info/WHEEL
djangorestframework_types-0.9.0.dist-info/RECORD
