Metadata-Version: 2.1
Name: djangorestframework-types
Version: 0.9.0
Summary: Type stubs for Django Rest Framework
Home-page: https://github.com/sbdchd/djangorestframework-types
License: MIT
Keywords: django,djangorestframework,types,mypy,stubs
Author: Steve Dignam
Author-email: steve@dignam.xyz
Requires-Python: >=3.8,<4.0
Classifier: License :: OSI Approved :: MIT License
Classifier: Programming Language :: Python :: 3
Classifier: Programming Language :: Python :: 3.8
Classifier: Programming Language :: Python :: 3.9
Classifier: Programming Language :: Python :: 3.10
Classifier: Programming Language :: Python :: 3.11
Classifier: Programming Language :: Python :: 3.12
Requires-Dist: typing_extensions (>=4.6,<5.0) ; python_version < "3.11"
Project-URL: Repository, https://github.com/sbdchd/djangorestframework-types
